pcap_anonymize/__init__.py
pcap_anonymize/__main__.py
pcap_anonymize/pcap_anonymize.py
pcap_anonymize/app_layer/__init__.py
pcap_anonymize/app_layer/coap.py
pcap_anonymize/app_layer/http.py
pcap_anonymize/app_layer/tplink.py
pcap_anonymize/mac/__init__.py
pcap_anonymize/mac/arp.py
pcap_anonymize/mac/dhcp.py
pcap_anonymize/mac/ether.py
pcap_anonymize/mac/utils.py
pcap_anonymize-0.3.0.dist-info/METADATA
pcap_anonymize-0.3.0.dist-info/WHEEL
pcap_anonymize-0.3.0.dist-info/entry_points.txt
pcap_anonymize-0.3.0.dist-info/top_level.txt
pcap_anonymize-0.3.0.dist-info/RECORD
